genie_flow_invoker/invoker/api.py
genie_flow_invoker_api-0.7.0.dist-info/licenses/NOTICES
genie_flow_invoker_api-0.7.0.dist-info/METADATA
genie_flow_invoker_api-0.7.0.dist-info/WHEEL
genie_flow_invoker_api-0.7.0.dist-info/top_level.txt
genie_flow_invoker_api-0.7.0.dist-info/RECORD
